onesharp/__init__.py
onesharp/interpreter/__init__.py
onesharp/interpreter/interpreter.py
onesharp/programs/__init__.py
onesharp/programs/add.py
onesharp/programs/add_unary.py
onesharp/programs/clear.py
onesharp/programs/compare.py
onesharp/programs/copy.py
onesharp/programs/diag.py
onesharp/programs/div.py
onesharp/programs/move.py
onesharp/programs/mult_unary.py
onesharp/programs/pow_unary.py
onesharp/programs/successor.py
onesharp/programs/universal.py
onesharp/programs/universal_alt.py
onesharp/programs/write.py
onesharp/tools/__init__.py
onesharp/tools/instruction_set.py
onesharp/tools/labels_to_offsets.py
onesharp/tools/ones.py
onesharp/tools/sanity.py
onesharp-0.0.2.dist-info/LICENSE
onesharp-0.0.2.dist-info/METADATA
onesharp-0.0.2.dist-info/WHEEL
onesharp-0.0.2.dist-info/top_level.txt
onesharp-0.0.2.dist-info/RECORD
